tsetdomocli/Monitor.py
tsetdomocli/__init__.py
tsetdomocli/__main__.py
tsetdomocli-1.6.dist-info/METADATA
tsetdomocli-1.6.dist-info/WHEEL
tsetdomocli-1.6.dist-info/entry_points.txt
tsetdomocli-1.6.dist-info/top_level.txt
tsetdomocli-1.6.dist-info/RECORD
