Metadata-Version: 2.1
Name: tsetdomocli
Version: 1.6
Summary: A cli tool for docker monitoring with prometheus and cAdvisor
Home-page: UNKNOWN
Author: Tianran Wei
Author-email: weitr.noah@gmail.com
License: UNKNOWN
Platform: UNKNOWN
Classifier: Programming Language :: Python :: 3
Classifier: License :: OSI Approved :: MIT License
Classifier: Operating System :: OS Independent
Requires-Python: >=3.6
Requires-Dist: numpy
Requires-Dist: hurry.filesize
Requires-Dist: requests
Requires-Dist: hurry
Requires-Dist: typer
Requires-Dist: docker
Requires-Dist: six
